build/__init__.py
build/__main__.py
build/_builder.py
build/_ctx.py
build/_exceptions.py
build/_types.py
build/_util.py
build/env.py
build/py.typed
build/util.py
build/_compat/__init__.py
build/_compat/importlib.py
build/_compat/tarfile.py
build/_compat/tomllib.py
build-1.2.0.dist-info/entry_points.txt
build-1.2.0.dist-info/LICENSE
build-1.2.0.dist-info/WHEEL
build-1.2.0.dist-info/METADATA
build-1.2.0.dist-info/RECORD
