Metadata-Version: 2.1
Name: build
Version: 1.2.0
Summary: A simple, correct Python build frontend
Author-email: Filipe Laíns <lains@riseup.net>, Bernát Gábor <gaborjbernat@gmail.com>, layday <layday@protonmail.com>, Henry Schreiner <henryschreineriii@gmail.com>
Requires-Python: >= 3.8
Classifier: License :: OSI Approved :: MIT License
Classifier: Programming Language :: Python :: 3
Classifier: Programming Language :: Python :: 3 :: Only
Classifier: Programming Language :: Python :: 3.8
Classifier: Programming Language :: Python :: 3.9
Classifier: Programming Language :: Python :: 3.10
Classifier: Programming Language :: Python :: 3.11
Classifier: Programming Language :: Python :: 3.12
Classifier: Programming Language :: Python :: Implementation :: CPython
Classifier: Programming Language :: Python :: Implementation :: PyPy
Requires-Dist: packaging >= 19.1
Requires-Dist: pyproject_hooks
Requires-Dist: colorama; os_name == "nt"
Requires-Dist: importlib-metadata >= 4.6; python_full_version < "3.10.2"
Requires-Dist: tomli >= 1.1.0; python_version < "3.11"
Requires-Dist: furo >= 2023.08.17 ; extra == "docs"
Requires-Dist: sphinx ~= 7.0 ; extra == "docs"
Requires-Dist: sphinx-argparse-cli >= 1.5 ; extra == "docs"
Requires-Dist: sphinx-autodoc-typehints >= 1.10 ; extra == "docs"
Requires-Dist: sphinx-issues >= 3.0.0 ; extra == "docs"
Requires-Dist: build[uv, virtualenv] ; extra == "test"
Requires-Dist: filelock >= 3 ; extra == "test"
Requires-Dist: pytest >= 6.2.4 ; extra == "test"
Requires-Dist: pytest-cov >= 2.12 ; extra == "test"
Requires-Dist: pytest-mock >= 2 ; extra == "test"
Requires-Dist: pytest-rerunfailures >= 9.1 ; extra == "test"
Requires-Dist: pytest-xdist >= 1.34 ; extra == "test"
Requires-Dist: wheel >= 0.36.0 ; extra == "test"
Requires-Dist: setuptools >= 42.0.0 ; extra == "test" and ( python_version < "3.10")
Requires-Dist: setuptools >= 56.0.0 ; extra == "test" and ( python_version == "3.10")
Requires-Dist: setuptools >= 56.0.0 ; extra == "test" and ( python_version == "3.11")
Requires-Dist: setuptools >= 67.8.0 ; extra == "test" and ( python_version >= "3.12")
Requires-Dist: build[uv] ; extra == "typing"
Requires-Dist: importlib-metadata >= 5.1 ; extra == "typing"
Requires-Dist: mypy ~= 1.9.0 ; extra == "typing"
Requires-Dist: tomli ; extra == "typing"
Requires-Dist: typing-extensions >= 3.7.4.3 ; extra == "typing"
Requires-Dist: uv >= 0.1.18 ; extra == "uv"
Requires-Dist: virtualenv >= 20.0.35 ; extra == "virtualenv"
Project-URL: changelog, https://build.pypa.io/en/stable/changelog.html
Project-URL: homepage, https://build.pypa.io
Project-URL: issues, https://github.com/pypa/build/issues
Project-URL: source, https://github.com/pypa/build
Provides-Extra: docs
Provides-Extra: test
Provides-Extra: typing
Provides-Extra: uv
Provides-Extra: virtualenv
